{
    "@class": "com.kony.gen.viz.model.component.KVizButton",
    "DNDConfig": null,
    "_height_": {
        "type": "string",
        "value": "46dp"
    },
    "_left_": {
        "type": "string",
        "value": "0"
    },
    "_margin_": [
        6,
        6,
        6,
        6
    ],
    "_padding_": [
        0,
        0,
        0,
        0
    ],
    "_skin_": "s807b7dac6c34105b19ab3acfcf10fee",
    "_text_": "Accept now",
    "_top_": {
        "type": "string",
        "value": "0%"
    },
    "_width_": {
        "type": "string",
        "value": "48.15%"
    },
    "canUpdateUI": true,
    "centerx": {
        "type": "string",
        "value": "50%"
    },
    "centery": {
        "type": "string",
        "value": "66.09%"
    },
    "containerweight": 100,
    "contentalignment": 5,
    "displaytext": true,
    "focusskin": "sca87a5dee9e41f69dddab89a0c060c4",
    "id": "claimBtn",
    "ide_onClick": "AS_Button_ebcb21b00aa646bfaf170514cb145e06",
    "info": null,
    "iscustomlayout": false,
    "isvisible": true,
    "kuid": "bbb238acc43d4e4b99f740416edeff5d",
    "name": "kony.ui.Button",
    "parent": "frmOffer",
    "pf": "frmOffer",
    "retaincontentalignment": false,
    "retainflexpositionproperties": false,
    "wType": "Button"
}